helix_connect/__init__.py
helix_connect/admin.py
helix_connect/consumer.py
helix_connect/exceptions.py
helix_connect/producer.py
helix_connect-1.1.9.dist-info/licenses/LICENSE
helix_connect-1.1.9.dist-info/METADATA
helix_connect-1.1.9.dist-info/WHEEL
helix_connect-1.1.9.dist-info/top_level.txt
helix_connect-1.1.9.dist-info/RECORD
