Metadata-Version: 2.4
Name: helix-connect
Version: 1.1.9
Summary: Official Python SDK for Helix Connect Data Marketplace
Author-email: Helix Tools <contact@helix.tools>
License: MIT
Project-URL: Homepage, https://helix-connect.com
Project-URL: Documentation, https://docs.helix-connect.com
Project-URL: Repository, https://github.com/helix-tools/helix-connect-sdk-python
Project-URL: Issues, https://github.com/helix-tools/helix-connect-sdk-python/issues
Keywords: helix,data-marketplace,s3,aws,datasets
Classifier: Development Status :: 4 - Beta
Classifier: Intended Audience :: Developers
Classifier: License :: OSI Approved :: MIT License
Classifier: Programming Language :: Python :: 3
Classifier: Programming Language :: Python :: 3.8
Classifier: Programming Language :: Python :: 3.9
Classifier: Programming Language :: Python :: 3.10
Classifier: Programming Language :: Python :: 3.11
Requires-Python: >=3.8
License-File: LICENSE
Requires-Dist: boto3>=1.28.0
Requires-Dist: botocore>=1.31.0
Requires-Dist: requests>=2.31.0
Requires-Dist: cryptography>=41.0.0
Requires-Dist: genson>=1.2.0
Provides-Extra: dev
Requires-Dist: pytest>=7.4.0; extra == "dev"
Requires-Dist: pytest-cov>=4.1.0; extra == "dev"
Requires-Dist: black>=23.7.0; extra == "dev"
Requires-Dist: mypy>=1.5.0; extra == "dev"
Requires-Dist: flake8>=6.1.0; extra == "dev"
Requires-Dist: jsonschema>=4.20.0; extra == "dev"
Dynamic: license-file
